pyabi/__init__.py
tests/__init__.py
tests/test_pyabi.py
PyABI-0.0.42.dist-info/LICENSE.md
PyABI-0.0.42.dist-info/METADATA
PyABI-0.0.42.dist-info/WHEEL
PyABI-0.0.42.dist-info/top_level.txt
PyABI-0.0.42.dist-info/RECORD
